MANIFEST.in
README.rst
setup.py
dataclean/__init__.py
dataclean/cleaning.py
dataclean/codegen.py
dataclean/manager.py
dataclean/pipeline.py
dataclean/widget.py
dataclean/static/iosbadge.js
dataclean/static/jquery.tablesorter.min.js
dataclean/static/main.css
dataclean/static/main.js
ipydataclean.egg-info/PKG-INFO
ipydataclean.egg-info/SOURCES.txt
ipydataclean.egg-info/dependency_links.txt
ipydataclean.egg-info/requires.txt
ipydataclean.egg-info/top_level.txt