Metadata-Version: 1.0
Name: ipydataclean
Version: 0.2.2
Summary: Interactive cleaning for pandas DataFrames
Home-page: https://github.com/facultyai/ipydataclean
Author: Faculty
Author-email: opensource@faculty.ai
License: Apache 2.0
Platform: UNKNOWN
